djfim/__init__.py
djfim/apps.py
djfim/base.py
djfim/depository.py
djfim/exception.py
djfim/extension.py
djfim/function.py
djfim/models.py
djfim/runtime.py
djfim/schema.py
djfim/settings.py
djfim/shortcut.py
djfim/solver.py
djfim/contrib/__init__.py
djfim/contrib/action.py
djfim/contrib/concrete.py
djfim/contrib/depot.py
djfim/contrib/diff.py
djfim/contrib/extraction.py
djfim/contrib/notary.py
djfim/contrib/partition.py
djfim/contrib/relation.py
djfim/contrib/schema.py
djfim/management/__init__.py
djfim/management/base.py
djfim-0.5.8.dist-info/METADATA
djfim-0.5.8.dist-info/WHEEL
djfim-0.5.8.dist-info/top_level.txt
djfim-0.5.8.dist-info/RECORD
