Metadata-Version: 2.1
Name: djfim
Version: 0.5.8
Summary: Django extension for flexible import and merge
Author-email: Cecelia Chen <cecelia@studio.home>
License: Apache License
Project-URL: Homepage, http://rcs.studio.home/project/djfim
Keywords: Django,persistency
Classifier: Development Status :: 4 - Beta
Classifier: Intended Audience :: Developers
Classifier: Intended Audience :: System Administrators
Classifier: License :: OSI Approved :: Apache Software License
Classifier: Programming Language :: Python
Classifier: Programming Language :: Python :: 3
Classifier: Programming Language :: Python :: 3 :: Only
Classifier: Topic :: Database
Classifier: Topic :: System :: Archiving
Classifier: Topic :: Software Development :: Libraries :: Python Modules
Requires-Python: >=3.7
Requires-Dist: Django (>3)
Requires-Dist: dmprj
Requires-Dist: dsgen
Requires-Dist: gpg
